README.txt
setup.py
MultiComplete.egg-info/PKG-INFO
MultiComplete.egg-info/SOURCES.txt
MultiComplete.egg-info/dependency_links.txt
MultiComplete.egg-info/entry_points.txt
MultiComplete.egg-info/not-zip-safe
MultiComplete.egg-info/paster_plugins.txt
MultiComplete.egg-info/requires.txt
MultiComplete.egg-info/sqlobject.txt
MultiComplete.egg-info/top_level.txt
multicomplete/__init__.py
multicomplete/release.py
multicomplete/widgets.py
multicomplete/templates/__init__.py
