Metadata-Version: 1.0
Name: MultiComplete
Version: 1.0
Summary: Multiple word completion within a single text field TG widget.
Home-page: http://www.turbogears.org/widgets/
Author: Hakan Bilgin, Kevin Dangoor
Author-email: dangoor+multicomplete@gmail.com
License: LGPL
Download-URL: http://www.turbogears.org/widgets/
Keywords: turbogears.widgets
Platform: UNKNOWN
Classifier: Development Status :: 3 - Alpha
Classifier: Operating System :: OS Independent
Classifier: Programming Language :: Python
Classifier: Topic :: Software Development :: Libraries :: Python Modules
Classifier: Framework :: TurboGears
Classifier: Framework :: TurboGears :: Widgets
